send_keys_to_vm.py
send_keys_to_vm-1.0.dist-info/DESCRIPTION.rst
send_keys_to_vm-1.0.dist-info/METADATA
send_keys_to_vm-1.0.dist-info/RECORD
send_keys_to_vm-1.0.dist-info/WHEEL
send_keys_to_vm-1.0.dist-info/metadata.json
send_keys_to_vm-1.0.dist-info/top_level.txt
