Metadata-Version: 2.0
Name: send-keys-to-vm
Version: 1.0
Summary: Send USB Scancodes to a VMware vSphere Virtual Machine
Home-page: UNKNOWN
Author: Alan J Castonguay
Author-email: alan@verselogic.net
License: Apache Software License 2.0
Platform: UNKNOWN
Classifier: Programming Language :: Python :: 2.7
Classifier: Programming Language :: Python :: 3
Classifier: Development Status :: 4 - Beta
Classifier: Natural Language :: English
Classifier: Intended Audience :: Information Technology
Classifier: Intended Audience :: System Administrators
Classifier: Intended Audience :: Developers
Classifier: License :: OSI Approved :: Apache Software License
Classifier: Operating System :: OS Independent
Classifier: Topic :: Software Development :: Libraries :: Python Modules
Requires-Dist: pyVmomi (>=6.5)
